flamma/__init__.py
flamma/menu.py
flamma-0.1.dist-info/LICENSE
flamma-0.1.dist-info/METADATA
flamma-0.1.dist-info/WHEEL
flamma-0.1.dist-info/entry_points.txt
flamma-0.1.dist-info/top_level.txt
flamma-0.1.dist-info/RECORD
